psconfig/__init__.py
psconfig/api.py
psconfig_client-0.1.7.dist-info/LICENSE
psconfig_client-0.1.7.dist-info/METADATA
psconfig_client-0.1.7.dist-info/WHEEL
psconfig_client-0.1.7.dist-info/top_level.txt
psconfig_client-0.1.7.dist-info/RECORD
