Metadata-Version: 2.1
Name: psconfig-client
Version: 0.1.7
Summary: psconfig/PWA configuration parser
Home-page: https://github.com/marian-babik/psconfig-client
Author: Marian Babik
Author-email: <marian.babik@cern.ch>
License: UNKNOWN
Platform: UNKNOWN
Classifier: Programming Language :: Python :: 3
Classifier: Programming Language :: Python :: 2
Classifier: License :: OSI Approved :: MIT License
Classifier: Operating System :: OS Independent
Requires-Python: >=2.7
Requires-Dist: requests
